<annotation verified="yes">
    <folder>Annotation</folder>
    <filename>btk_00264.jpg</filename>
    <path>THK_products-PascalVOC-export/Annotations/btk_00264.jpg</path>
    <source>
        <database>Unknown</database>
    </source>
    <size>
        <width>320</width>
        <height>320</height>
        <depth>3</depth>
    </size>
    <segmented>0</segmented>
    <object>
    <name>btk</name>
    <pose>Unspecified</pose>
    <truncated>0</truncated>
    <difficult>0</difficult>
    <bndbox>
        <xmin>3.463203463203463</xmin>
        <ymin>13.506493506493506</ymin>
        <xmax>107.35930735930737</xmax>
        <ymax>123.98268398268397</ymax>
    </bndbox>
</object>
</annotation>
