<annotation verified="yes">
    <folder>Annotation</folder>
    <filename>btk_00032.jpg</filename>
    <path>THK_products-PascalVOC-export/Annotations/btk_00032.jpg</path>
    <source>
        <database>Unknown</database>
    </source>
    <size>
        <width>320</width>
        <height>320</height>
        <depth>3</depth>
    </size>
    <segmented>0</segmented>
    <object>
    <name>btk</name>
    <pose>Unspecified</pose>
    <truncated>0</truncated>
    <difficult>0</difficult>
    <bndbox>
        <xmin>30.060606060606062</xmin>
        <ymin>45.2987012987013</ymin>
        <xmax>272.5541125541125</xmax>
        <ymax>114.28571428571428</ymax>
    </bndbox>
</object>
</annotation>
