<annotation verified="yes">
    <folder>Annotation</folder>
    <filename>hcr_00200.jpg</filename>
    <path>THK_products-PascalVOC-export/Annotations/hcr_00200.jpg</path>
    <source>
        <database>Unknown</database>
    </source>
    <size>
        <width>320</width>
        <height>320</height>
        <depth>3</depth>
    </size>
    <segmented>0</segmented>
    <object>
    <name>hcr</name>
    <pose>Unspecified</pose>
    <truncated>0</truncated>
    <difficult>0</difficult>
    <bndbox>
        <xmin>0</xmin>
        <ymin>21.818181818181817</ymin>
        <xmax>317.05627705627705</xmax>
        <ymax>160.34632034632034</ymax>
    </bndbox>
</object>
</annotation>
