<annotation verified="yes">
    <folder>Annotation</folder>
    <filename>hdr25_00668.jpg</filename>
    <path>THK_products-PascalVOC-export/Annotations/hdr25_00668.jpg</path>
    <source>
        <database>Unknown</database>
    </source>
    <size>
        <width>320</width>
        <height>320</height>
        <depth>3</depth>
    </size>
    <segmented>0</segmented>
    <object>
    <name>hdr</name>
    <pose>Unspecified</pose>
    <truncated>0</truncated>
    <difficult>0</difficult>
    <bndbox>
        <xmin>31.515151515151516</xmin>
        <ymin>46.4069264069264</ymin>
        <xmax>318.6147186147186</xmax>
        <ymax>135.4112554112554</ymax>
    </bndbox>
</object>
</annotation>
