<annotation verified="yes">
    <folder>Annotation</folder>
    <filename>hdr25_00215.jpg</filename>
    <path>THK_products-PascalVOC-export/Annotations/hdr25_00215.jpg</path>
    <source>
        <database>Unknown</database>
    </source>
    <size>
        <width>320</width>
        <height>320</height>
        <depth>3</depth>
    </size>
    <segmented>0</segmented>
    <object>
    <name>hdr</name>
    <pose>Unspecified</pose>
    <truncated>0</truncated>
    <difficult>0</difficult>
    <bndbox>
        <xmin>1.7316017316017316</xmin>
        <ymin>43.290043290043286</ymin>
        <xmax>320</xmax>
        <ymax>107.012987012987</ymax>
    </bndbox>
</object><object>
    <name>gsr</name>
    <pose>Unspecified</pose>
    <truncated>0</truncated>
    <difficult>0</difficult>
    <bndbox>
        <xmin>67.53246753246754</xmin>
        <ymin>32.20779220779221</ymin>
        <xmax>258.35497835497836</xmax>
        <ymax>51.6017316017316</ymax>
    </bndbox>
</object>
</annotation>
